LICENSE
README.md
setup.cfg
setup.py
flamiche/__init__.py
flamiche.egg-info/PKG-INFO
flamiche.egg-info/SOURCES.txt
flamiche.egg-info/dependency_links.txt
flamiche.egg-info/top_level.txt